rancon/__init__.py
rancon/__main__.py
rancon/common.py
rancon/service.py
rancon/settings.py
rancon/tools.py
rancon/version.py
rancon/backends/__init__.py
rancon/backends/consul.py
rancon/sources/__init__.py
rancon/sources/rancher.py
rancon-0.17.1.dist-info/DESCRIPTION.rst
rancon-0.17.1.dist-info/METADATA
rancon-0.17.1.dist-info/RECORD
rancon-0.17.1.dist-info/WHEEL
rancon-0.17.1.dist-info/entry_points.txt
rancon-0.17.1.dist-info/metadata.json
rancon-0.17.1.dist-info/top_level.txt
test/__init__.py
test/test_consul_backend.py
test/test_data.py
test/test_http_endpoints.py
test/test_main_loop.py
