Metadata-Version: 2.0
Name: rancon
Version: 0.17.1
Summary: A python tool which adds Rancher services to Consul based on label selectors
Home-page: https://github.com/flypenguin/python-rancon
Author: Axel Bock
Author-email: mr.axel.bock@gmail.com
License: UNKNOWN
Download-URL: https://github.com/flypenguin/python-rancon/tarball/0.17.1
Keywords: rancher,api,consul
Platform: UNKNOWN
Classifier: License :: OSI Approved :: MIT License
Classifier: Development Status :: 4 - Beta
Classifier: Intended Audience :: Developers
Classifier: Intended Audience :: System Administrators
Classifier: Programming Language :: Python :: 2
Classifier: Programming Language :: Python :: 3
Classifier: Operating System :: POSIX
Classifier: Operating System :: MacOS
Classifier: Topic :: System :: Systems Administration
Requires-Dist: cattleprod (>=0.6.0)
Requires-Dist: python-consul (==0.6.0)
Requires-Dist: dotmap (~=1.0)
Requires-Dist: requests (~=2.0)
Requires-Dist: sanic (~=0.0)
Requires-Dist: uvloop (~=0.0)
Requires-Dist: prometheus-client (~=0.0)
Requires-Dist: aiohttp (~=2.0)
